pyx12/__init__.py
pyx12/codes.py
pyx12/dataele.py
pyx12/decorators.py
pyx12/errh_xml.py
pyx12/error_997.py
pyx12/error_999.py
pyx12/error_debug.py
pyx12/error_handler.py
pyx12/error_html.py
pyx12/error_item.py
pyx12/error_visitor.py
pyx12/errors.py
pyx12/map_if.py
pyx12/map_index.py
pyx12/map_override.py
pyx12/map_walker.py
pyx12/nodeCounter.py
pyx12/params.py
pyx12/path.py
pyx12/rawx12file.py
pyx12/segment.py
pyx12/syntax.py
pyx12/validation.py
pyx12/version.py
pyx12/x12context.py
pyx12/x12file.py
pyx12/x12metadata.py
pyx12/x12n_document.py
pyx12/x12xml.py
pyx12/x12xml_simple.py
pyx12/xmlwriter.py
pyx12/xmlx12_simple.py
pyx12/map/270.4010.X092.A1.xml
pyx12/map/271.4010.X092.A1.xml
pyx12/map/276.4010.X093.A1.xml
pyx12/map/277.4010.X093.A1.xml
pyx12/map/277.5010.X212.xml
pyx12/map/277.5010.X214.xml
pyx12/map/277U.4010.X070.xml
pyx12/map/278.4010.X094.27.A1.xml
pyx12/map/278.4010.X094.A1.xml
pyx12/map/820.4010.X061.A1.xml
pyx12/map/820.5010.X218.v2.xml
pyx12/map/820.5010.X218.xml
pyx12/map/830.4010.PS.xml
pyx12/map/834.4010.X095.A1.xml
pyx12/map/834.5010.X220.A1.v2.xml
pyx12/map/834.5010.X220.A1.xml
pyx12/map/835.4010.X091.A1.xml
pyx12/map/835.5010.X221.A1.v2.xml
pyx12/map/835.5010.X221.A1.xml
pyx12/map/837.4010.X096.A1.xml
pyx12/map/837.4010.X097.A1.xml
pyx12/map/837.4010.X098.A1.xml
pyx12/map/837.5010.X222.A1.xml
pyx12/map/837Q3.I.5010.X223.A1.v2.xml
pyx12/map/837Q3.I.5010.X223.A1.xml
pyx12/map/841.4010.XXXC.xml
pyx12/map/997.4010.xml
pyx12/map/999.5010.xml
pyx12/map/999.5010X231.A1.xml
pyx12/map/codes.xml
pyx12/map/codes.xsd
pyx12/map/comp_test.xml
pyx12/map/dataele.xml
pyx12/map/dataele.xsd
pyx12/map/map.v2.xsd
pyx12/map/map.xsd
pyx12/map/maps.xml
pyx12/map/maps.xsd
pyx12/map/x12.control.00401.xml
pyx12/map/x12.control.00501.xml
pyx12/scripts/__init__.py
pyx12/scripts/x12html.py
pyx12/scripts/x12info.py
pyx12/scripts/x12norm.py
pyx12/scripts/x12valid.py
pyx12/scripts/x12xml.py
pyx12-2.3.3.dist-info/DESCRIPTION.rst
pyx12-2.3.3.dist-info/METADATA
pyx12-2.3.3.dist-info/RECORD
pyx12-2.3.3.dist-info/WHEEL
pyx12-2.3.3.dist-info/entry_points.txt
pyx12-2.3.3.dist-info/metadata.json
pyx12-2.3.3.dist-info/top_level.txt
